lm_notehub-0.4.0.dist-info/licenses/LICENSE
notehub/__init__.py
notehub/__main__.py
notehub/cache.py
notehub/cli.py
notehub/config.py
notehub/context.py
notehub/gh_wrapper.py
notehub/utils.py
notehub/commands/__init__.py
notehub/commands/add.py
notehub/commands/edit.py
notehub/commands/find.py
notehub/commands/list.py
notehub/commands/move.py
notehub/commands/show.py
notehub/commands/status.py
notehub/commands/sync.py
lm_notehub-0.4.0.dist-info/METADATA
lm_notehub-0.4.0.dist-info/WHEEL
lm_notehub-0.4.0.dist-info/entry_points.txt
lm_notehub-0.4.0.dist-info/top_level.txt
lm_notehub-0.4.0.dist-info/RECORD
